examples/__init__.py
nkululeko/__init__.py
nkululeko/aug_train.py
nkululeko/augment.py
nkululeko/balance.py
nkululeko/constants.py
nkululeko/demo.py
nkululeko/demo_predictor.py
nkululeko/ensemble.py
nkululeko/experiment.py
nkululeko/explore.py
nkululeko/export.py
nkululeko/feature_demo.py
nkululeko/feature_extractor.py
nkululeko/file_checker.py
nkululeko/filter_data.py
nkululeko/fixedsegment.py
nkululeko/flags.py
nkululeko/glob_conf.py
nkululeko/modelrunner.py
nkululeko/multidb.py
nkululeko/nkululeko.py
nkululeko/optim.py
nkululeko/optimizationrunner.py
nkululeko/plots.py
nkululeko/predict.py
nkululeko/resample.py
nkululeko/runmanager.py
nkululeko/scaler.py
nkululeko/segment.py
nkululeko/testing.py
nkululeko/testing_predictor.py
nkululeko/testing_pretrain.py
nkululeko/augmenting/__init__.py
nkululeko/augmenting/augmenter_audiomentations.py
nkululeko/augmenting/augmenter_auglib.py
nkululeko/augmenting/randomsplicer.py
nkululeko/augmenting/randomsplicing.py
nkululeko/augmenting/resampler.py
nkululeko/autopredict/__init__.py
nkululeko/autopredict/ap_age.py
nkululeko/autopredict/ap_arousal.py
nkululeko/autopredict/ap_dominance.py
nkululeko/autopredict/ap_emotion.py
nkululeko/autopredict/ap_gender.py
nkululeko/autopredict/ap_mos.py
nkululeko/autopredict/ap_pesq.py
nkululeko/autopredict/ap_sdr.py
nkululeko/autopredict/ap_sid.py
nkululeko/autopredict/ap_snr.py
nkululeko/autopredict/ap_stoi.py
nkululeko/autopredict/ap_text.py
nkululeko/autopredict/ap_textclassifier.py
nkululeko/autopredict/ap_translate.py
nkululeko/autopredict/ap_valence.py
nkululeko/autopredict/estimate_snr.py
nkululeko/autopredict/google_translator.py
nkululeko/autopredict/whisper_transcriber.py
nkululeko/autopredict/tests/__init__.py
nkululeko/autopredict/tests/test_whisper_transcriber.py
nkululeko/data/__init__.py
nkululeko/data/dataset.py
nkululeko/data/dataset_csv.py
nkululeko/feat_extract/__init__.py
nkululeko/feat_extract/feats_agender.py
nkululeko/feat_extract/feats_agender_agender.py
nkululeko-1.1.9.dist-info/licenses/LICENSE
nkululeko-1.1.9.dist-info/METADATA
nkululeko-1.1.9.dist-info/WHEEL
nkululeko-1.1.9.dist-info/entry_points.txt
nkululeko-1.1.9.dist-info/top_level.txt
nkululeko-1.1.9.dist-info/RECORD
