Metadata-Version: 2.4
Name: nkululeko
Version: 1.1.9
Summary: Machine learning audio prediction experiments based on templates
Home-page: https://github.com/felixbur/nkululeko
Author: Felix Burkhardt
Author-email: Felix Burkhardt <fxburk@gmail.com>, Bagus Tris Atmaja <btatmaja@gmail.com>
License: MIT
Project-URL: Homepage, https://github.com/felixbur/nkululeko
Project-URL: Repository, https://github.com/felixbur/nkululeko
Project-URL: Documentation, https://github.com/felixbur/nkululeko
Project-URL: Issues, https://github.com/felixbur/nkululeko/issues
Keywords: machine learning,audio,emotion recognition,speech processing
Classifier: Development Status :: 4 - Beta
Classifier: Intended Audience :: Developers
Classifier: Intended Audience :: Science/Research
Classifier: License :: OSI Approved :: MIT License
Classifier: Programming Language :: Python :: 3
Classifier: Programming Language :: Python :: 3.9
Classifier: Programming Language :: Python :: 3.10
Classifier: Programming Language :: Python :: 3.11
Classifier: Programming Language :: Python :: 3.12
Classifier: Topic :: Scientific/Engineering :: Artificial Intelligence
Classifier: Topic :: Multimedia :: Sound/Audio :: Analysis
Requires-Python: >=3.9
License-File: LICENSE
Requires-Dist: audb>=1.11.4
Requires-Dist: audeer>=1.0.0
Requires-Dist: audformat>=1.3.1
Requires-Dist: audplot
Requires-Dist: audmodel
Requires-Dist: auglib>=1.0.4
Requires-Dist: audinterface>=1.0.0
Requires-Dist: audiofile>=1.0.0
Requires-Dist: audiomentations>=0.42.0
Requires-Dist: audmetric>=1.0.0
Requires-Dist: audonnx>=0.7.0
Requires-Dist: confidence-intervals>=0.0.2
Requires-Dist: datasets>=2.0.0
Requires-Dist: googletrans==4.0.2
Requires-Dist: imageio>=2.0.0
Requires-Dist: matplotlib>=3.0.0
Requires-Dist: numpy>=1.20.0
Requires-Dist: numpy_audio_limiter
Requires-Dist: opensmile>=2.0.0
Requires-Dist: pandas<3.0.0
Requires-Dist: praat-parselmouth>=0.4.0
Requires-Dist: scikit-learn>=1.0.0
Requires-Dist: scipy>=1.0.0
Requires-Dist: seaborn>=0.11.0
Requires-Dist: sentencepiece==0.2.1
Requires-Dist: shap==0.50.0
Requires-Dist: sounddevice>=0.4.0
Requires-Dist: splitutils
Requires-Dist: torchaudio==2.6.0
Requires-Dist: torchvision==0.21.0
Requires-Dist: torch==2.6.0
Requires-Dist: transformers>=4.0.0
Requires-Dist: umap-learn>=0.5.0
Requires-Dist: xgboost>=1.0.0
Requires-Dist: pylatex>=1.0.0
Provides-Extra: torch
Requires-Dist: torch>=1.0.0; extra == "torch"
Requires-Dist: torchvision>=0.10.0; extra == "torch"
Requires-Dist: torchaudio>=0.10.0; extra == "torch"
Provides-Extra: torch-cpu
Requires-Dist: torch>=1.0.0; extra == "torch-cpu"
Requires-Dist: torchvision>=0.10.0; extra == "torch-cpu"
Requires-Dist: torchaudio>=0.10.0; extra == "torch-cpu"
Provides-Extra: spotlight
Requires-Dist: renumics-spotlight>=1.6.13; extra == "spotlight"
Requires-Dist: sliceguard>=0.0.35; extra == "spotlight"
Provides-Extra: tensorflow
Requires-Dist: tensorflow>=2.0.0; extra == "tensorflow"
Requires-Dist: tensorflow-hub>=0.12.0; extra == "tensorflow"
Provides-Extra: all
Requires-Dist: torch>=1.0.0; extra == "all"
Requires-Dist: torchvision>=0.10.0; extra == "all"
Requires-Dist: torchaudio>=0.10.0; extra == "all"
Requires-Dist: renumics-spotlight>=1.6.13; extra == "all"
Requires-Dist: sliceguard>=0.0.35; extra == "all"
Requires-Dist: tensorflow>=2.0.0; extra == "all"
Requires-Dist: tensorflow-hub>=0.12.0; extra == "all"
Requires-Dist: shap>=0.40.0; extra == "all"
Requires-Dist: imblearn>=0.0.0; extra == "all"
Requires-Dist: cylimiter>=0.0.1; extra == "all"
Requires-Dist: audtorch>=0.0.1; extra == "all"
Requires-Dist: splitutils>=0.0.1; extra == "all"
Dynamic: author
Dynamic: home-page
Dynamic: license-file
Dynamic: requires-python
